langtools_mcp/__init__.py
langtools_mcp/logger.py
langtools_mcp/server.py
langtools_mcp/langtools/__init__.py
langtools_mcp/langtools/analysis.py
langtools_mcp/langtools/langtools_daemon_client.py
langtools_mcp/langtools/parsers.py
langtools_mcp/langtools/settings.py
langtools_mcp/langtools/strategies.py
langtools_mcp/langtools/tool_runner.py
langtools_mcp/langtools/utils.py
langtools_mcp/langtools_daemon/lsp_pool.py
langtools_mcp/langtools_daemon/main.py
mseep_langtools_mcp-0.1.3.dist-info/licenses/LICENSE
mseep_langtools_mcp-0.1.3.dist-info/METADATA
mseep_langtools_mcp-0.1.3.dist-info/WHEEL
mseep_langtools_mcp-0.1.3.dist-info/entry_points.txt
mseep_langtools_mcp-0.1.3.dist-info/top_level.txt
mseep_langtools_mcp-0.1.3.dist-info/RECORD
