Metadata-Version: 2.4
Name: mseep-langtools-mcp
Version: 0.1.3
Summary: Add your description here
Author-email: mseep <support@skydeck.ai>
Requires-Python: >=3.13
License-File: LICENSE
Requires-Dist: mcp[cli]>=1.8.1
Requires-Dist: pydantic-settings>=2.10.1
Requires-Dist: ruff>=0.12.1
Provides-Extra: test
Requires-Dist: pytest>=8.4.1; extra == "test"
Dynamic: license-file
